{
    "content": null,
    "embeds": [
        {
            "title": "The following domain will expire soon:",
            "color": 15651330,
            "fields": [
                {
                    "name": "Domain",
                    "value": "example.com",
                    "inline": true
                },
                {
                    "name": "Expiration",
                    "value": "9 Days",
                    "inline": true
                }
            ],
            "timestamp": "2022-07-09T14:02:00.000Z"
        }
    ],
    "attachments": []
}